LICENSE
MANIFEST.in
README.md
pyproject.toml
requirements.txt
setup.py
csrc/activation.cpp
csrc/activation_kernels.cu
csrc/attention.cpp
csrc/cache.cpp
csrc/cache_kernels.cu
csrc/layernorm.cpp
csrc/layernorm_kernels.cu
csrc/pos_encoding.cpp
csrc/pos_encoding_kernels.cu
csrc/reduction_utils.cuh
csrc/attention/attention_dtypes.h
csrc/attention/attention_generic.cuh
csrc/attention/attention_kernels.cu
csrc/attention/attention_utils.cuh
csrc/attention/dtype_bfloat16.cuh
csrc/attention/dtype_float16.cuh
csrc/attention/dtype_float32.cuh
vllm/__init__.py
vllm/block.py
vllm/config.py
vllm/logger.py
vllm/outputs.py
vllm/sampling_params.py
vllm/sequence.py
vllm/utils.py
vllm/core/__init__.py
vllm/core/block_manager.py
vllm/core/policy.py
vllm/core/scheduler.py
vllm/engine/__init__.py
vllm/engine/arg_utils.py
vllm/engine/async_llm_engine.py
vllm/engine/llm_engine.py
vllm/engine/ray_utils.py
vllm/engine/tokenizer_utils.py
vllm/entrypoints/__init__.py
vllm/entrypoints/api_server.py
vllm/entrypoints/llm.py
vllm/entrypoints/openai/__init__.py
vllm/entrypoints/openai/api_server.py
vllm/entrypoints/openai/protocol.py
vllm/model_executor/__init__.py
vllm/model_executor/input_metadata.py
vllm/model_executor/model_loader.py
vllm/model_executor/utils.py
vllm/model_executor/weight_utils.py
vllm/model_executor/layers/__init__.py
vllm/model_executor/layers/activation.py
vllm/model_executor/layers/attention.py
vllm/model_executor/layers/layernorm.py
vllm/model_executor/layers/sampler.py
vllm/model_executor/models/__init__.py
vllm/model_executor/models/gpt2.py
vllm/model_executor/models/gpt_neox.py
vllm/model_executor/models/llama.py
vllm/model_executor/models/opt.py
vllm/model_executor/parallel_utils/__init__.py
vllm/model_executor/parallel_utils/parallel_state.py
vllm/model_executor/parallel_utils/tensor_parallel/__init__.py
vllm/model_executor/parallel_utils/tensor_parallel/layers.py
vllm/model_executor/parallel_utils/tensor_parallel/mappings.py
vllm_py.egg-info/PKG-INFO
vllm_py.egg-info/SOURCES.txt
vllm_py.egg-info/dependency_links.txt
vllm_py.egg-info/requires.txt
vllm_py.egg-info/top_level.txt